malwoverview/__init__.py
malwoverview/malwoverview.py
malwoverview/modules/__init__.py
malwoverview/modules/alienvault.py
malwoverview/modules/android.py
malwoverview/modules/bazaar.py
malwoverview/modules/bgpview.py
malwoverview/modules/configvars.py
malwoverview/modules/hybrid.py
malwoverview/modules/ipinfo.py
malwoverview/modules/malpedia.py
malwoverview/modules/malshare.py
malwoverview/modules/multipleip.py
malwoverview/modules/nist.py
malwoverview/modules/polyswarm.py
malwoverview/modules/threatfox.py
malwoverview/modules/triage.py
malwoverview/modules/urlhaus.py
malwoverview/modules/virustotal.py
malwoverview/utils/__init__.py
malwoverview/utils/colors.py
malwoverview/utils/hash.py
malwoverview/utils/peinfo.py
malwoverview/utils/utils.py
malwoverview-7.0.1.dist-info/licenses/LICENSE
malwoverview-7.0.1.dist-info/METADATA
malwoverview-7.0.1.dist-info/WHEEL
malwoverview-7.0.1.dist-info/entry_points.txt
malwoverview-7.0.1.dist-info/top_level.txt
malwoverview-7.0.1.dist-info/RECORD
