Metadata-Version: 2.4
Name: malwoverview
Version: 7.0.1
Summary: Malwoverview is a first response tool for threat hunting.
Author-email: Alexandre Borges <reverseexploit@proton.me>
License-Expression: GPL-3.0-or-later
Project-URL: Homepage, https://github.com/alexandreborges/malwoverview
Project-URL: Repository, https://github.com/alexandreborges/malwoverview
Classifier: Operating System :: OS Independent
Classifier: Programming Language :: Python :: 3
Classifier: Programming Language :: Python :: 3.8
Classifier: Programming Language :: Python :: 3.9
Classifier: Programming Language :: Python :: 3.10
Classifier: Programming Language :: Python :: 3.11
Classifier: Programming Language :: Python :: 3.12
Requires-Python: >=3.8
License-File: LICENSE
Requires-Dist: pefile
Requires-Dist: colorama
Requires-Dist: python-magic>=0.4.25; platform_system == "Linux" or platform_system == "Darwin"
Requires-Dist: python-magic-bin>=0.4.14; platform_system == "Windows"
Requires-Dist: simplejson
Requires-Dist: requests
Requires-Dist: validators
Requires-Dist: geocoder
Requires-Dist: polyswarm-api
Dynamic: license-file
